{
  "functions": {
    "function1": {
      "description": "First Lambda function",
      "source_dir": "lambdas/function1"
    },
    "function2": {
      "description": "Second Lambda function", 
      "source_dir": "lambdas/function2"
    }
  },
  "layers": {
    "common-libs": {
      "description": "Common libraries layer",
      "source_dir": "layers/common-libs"
    },
    "data-processing": {
      "description": "Data processing layer",
      "source_dir": "layers/data-processing"
    }
  }
}